[
  {
    "title": "node"
  },
  {
    "title": "react"
  },
  {
    "title": "golang"
  },
  {
    "title": "javascript"
  },
  {
    "title": "ruby"
  },
  {
    "title": "elixir"
  },
  {
    "title": "expressjs"
  },
  {
    "title": "nestjs"
  },
  {
    "title": "nextjs"
  },
  {
    "title": "vuejs"
  },
  {
    "title": "vuejs"
  },
  {
    "title": "mongodb"
  },
  {
    "title": "postgresql"
  },
  {
    "title": "prisma"
  },
  {
    "title": "graphql"
  },
  {
    "title": "apollo"
  },
  {
    "title": "docker"
  },
  {
    "title": "kubernetes"
  },
  {
    "title": "grafana"
  },
  {
    "title": "AWS"
  },
  {
    "title": "typescript"
  }
]
